{
  "paper_id": "lung_LDCT_traditional_086",
  "pmid": "36672655",
  "title": "Artificial Intelligence Assisted Computational Tomographic Detection of Lung Nodules for Prognostic Cancer Examination: A Large-Scale Clinical Trial.",
  "year": null,
  "journal": "Biomedicines",
  "doi": "10.3390/biomedicines11010147",
  "cancer_type": "lung",
  "category": "LDCT_traditional",
  "study_design": "other",
  "cohort_type": "screening",
  "sample_size": null,
  "input_modalities": [
    "LDCT",
    "CT"
  ],
  "model_type": "other",
  "performance_raw": {
    "auc": 0.88,
    "sensitivity": 0.04,
    "specificity": null,
    "early_stage_sensitivity": null
  },
  "has_stage_info": false,
  "validation_type": "none",
  "notes": "Remapped from original lung library.",
  "quality_flags": {
    "screening_relevant": true,
    "has_external_validation": false,
    "case_control_design": false,
    "impact_factor": null,
    "if_above_10": null,
    "if_unknown": true,
    "tier": "unknown"
  }
}