{
  "paper_id": "lung_cfDNA_traditional_023",
  "pmid": "29496499",
  "title": "Assessment of Plasma Proteomics Biomarker's Ability to Distinguish Benign From Malignant Lung Nodules: Results of the PANOPTIC (Pulmonary Nodule Plasma Proteomic Classifier) Trial.",
  "year": null,
  "journal": "Chest",
  "doi": "10.1016/j.chest.2018.02.012",
  "cancer_type": "lung",
  "category": "cfDNA_traditional",
  "study_design": "prospective_cohort",
  "cohort_type": "clinical",
  "sample_size": 685,
  "input_modalities": [
    "proteomics"
  ],
  "model_type": "other_ML",
  "performance_raw": {
    "auc": null,
    "sensitivity": 0.97,
    "specificity": 0.44,
    "early_stage_sensitivity": null
  },
  "has_stage_info": false,
  "validation_type": "none",
  "notes": "Remapped from original lung library. [Recategorized from LDCT to cfDNA_traditional: no CT modality detected]",
  "quality_flags": {
    "screening_relevant": true,
    "has_external_validation": false,
    "case_control_design": false,
    "impact_factor": 9.6,
    "if_above_10": false,
    "if_unknown": false,
    "tier": "extended"
  }
}